{
  "bitcoin": [
    {
      "timestamp": "2025-11-26T19:19:52.831203",
      "price": 89906,
      "change_24h": 3.508340251169434
    },
    {
      "timestamp": "2025-11-26T19:29:42.193604",
      "price": 89801,
      "change_24h": 4.158155518008173
    },
    {
      "timestamp": "2025-11-26T19:40:04.268482",
      "price": 89851,
      "change_24h": 4.182050323899075
    },
    {
      "timestamp": "2025-11-26T19:50:02.881652",
      "price": 89868,
      "change_24h": 3.8188332437500137
    },
    {
      "timestamp": "2025-11-26T19:59:46.556976",
      "price": 89982,
      "change_24h": 3.714369408430392
    },
    {
      "timestamp": "2025-11-26T20:28:58.306064",
      "price": 89961,
      "change_24h": 3.5185357551878944
    },
    {
      "timestamp": "2025-11-26T20:41:53.693655",
      "price": 89852,
      "change_24h": 3.060349861569962
    },
    {
      "timestamp": "2025-11-26T20:52:01.937565",
      "price": 89742,
      "change_24h": 2.8264028001006696
    },
    {
      "timestamp": "2025-11-26T21:09:47.150542",
      "price": 89874,
      "change_24h": 3.1932258816358576
    },
    {
      "timestamp": "2025-11-26T21:28:24.077301",
      "price": 90190,
      "change_24h": 3.3467931222373424
    }
  ],
  "cardano": [
    {
      "timestamp": "2025-11-26T19:19:52.831203",
      "price": 0.434229,
      "change_24h": 5.069599803815163
    },
    {
      "timestamp": "2025-11-26T19:29:42.193604",
      "price": 0.433595,
      "change_24h": 5.283370154886375
    },
    {
      "timestamp": "2025-11-26T19:40:04.268482",
      "price": 0.433719,
      "change_24h": 5.25392401667085
    },
    {
      "timestamp": "2025-11-26T19:50:02.881652",
      "price": 0.433269,
      "change_24h": 5.224385850626881
    },
    {
      "timestamp": "2025-11-26T19:59:46.556976",
      "price": 0.434346,
      "change_24h": 4.701989269613562
    },
    {
      "timestamp": "2025-11-26T20:28:58.306064",
      "price": 0.434319,
      "change_24h": 3.8981530440874246
    },
    {
      "timestamp": "2025-11-26T20:41:53.693655",
      "price": 0.434118,
      "change_24h": 3.2904340967572123
    },
    {
      "timestamp": "2025-11-26T20:52:01.937565",
      "price": 0.43323,
      "change_24h": 2.832486606364389
    },
    {
      "timestamp": "2025-11-26T21:09:47.150542",
      "price": 0.433248,
      "change_24h": 3.3306250531035184
    },
    {
      "timestamp": "2025-11-26T21:28:24.077301",
      "price": 0.432762,
      "change_24h": 3.208012074688196
    }
  ],
  "ethereum": [
    {
      "timestamp": "2025-11-26T19:19:52.831203",
      "price": 3021.81,
      "change_24h": 4.185350740716311
    },
    {
      "timestamp": "2025-11-26T19:29:42.193604",
      "price": 3025.78,
      "change_24h": 4.937080669911253
    },
    {
      "timestamp": "2025-11-26T19:40:04.268482",
      "price": 3031.02,
      "change_24h": 4.835308188099381
    },
    {
      "timestamp": "2025-11-26T19:50:02.881652",
      "price": 3030.87,
      "change_24h": 4.188377284047064
    },
    {
      "timestamp": "2025-11-26T19:59:46.556976",
      "price": 3034.11,
      "change_24h": 3.8271023073512356
    },
    {
      "timestamp": "2025-11-26T20:28:58.306064",
      "price": 3020.83,
      "change_24h": 3.1540256241107385
    },
    {
      "timestamp": "2025-11-26T20:41:53.693655",
      "price": 3017.93,
      "change_24h": 2.9382427578872066
    },
    {
      "timestamp": "2025-11-26T20:52:01.937565",
      "price": 3016.49,
      "change_24h": 2.8178139463814222
    },
    {
      "timestamp": "2025-11-26T21:09:47.150542",
      "price": 3020.94,
      "change_24h": 3.212538386917909
    },
    {
      "timestamp": "2025-11-26T21:28:24.077301",
      "price": 3026.72,
      "change_24h": 3.1053378064794668
    }
  ],
  "litecoin": [
    {
      "timestamp": "2025-11-26T19:19:52.831203",
      "price": 86.5,
      "change_24h": 1.7444685837826606
    },
    {
      "timestamp": "2025-11-26T19:29:42.193604",
      "price": 86.45,
      "change_24h": 1.9033273272858469
    },
    {
      "timestamp": "2025-11-26T19:40:04.268482",
      "price": 86.55,
      "change_24h": 2.0083103616479345
    },
    {
      "timestamp": "2025-11-26T19:50:02.881652",
      "price": 86.59,
      "change_24h": 1.7081946947973197
    },
    {
      "timestamp": "2025-11-26T19:59:46.556976",
      "price": 86.57,
      "change_24h": 1.4077827071381066
    },
    {
      "timestamp": "2025-11-26T20:28:58.306064",
      "price": 86.42,
      "change_24h": 1.133256103467193
    },
    {
      "timestamp": "2025-11-26T20:41:53.693655",
      "price": 86.35,
      "change_24h": 0.7284583857706013
    },
    {
      "timestamp": "2025-11-26T20:52:01.937565",
      "price": 86.39,
      "change_24h": 0.6358156372655133
    },
    {
      "timestamp": "2025-11-26T21:09:47.150542",
      "price": 86.61,
      "change_24h": 0.8957556389832844
    },
    {
      "timestamp": "2025-11-26T21:28:24.077301",
      "price": 86.57,
      "change_24h": 1.2222000594355449
    }
  ],
  "solana": [
    {
      "timestamp": "2025-11-26T19:19:52.831203",
      "price": 144.02,
      "change_24h": 6.418948772466289
    },
    {
      "timestamp": "2025-11-26T19:29:42.193604",
      "price": 144.12,
      "change_24h": 7.170937986945047
    },
    {
      "timestamp": "2025-11-26T19:40:04.268482",
      "price": 144.24,
      "change_24h": 6.883898911433399
    },
    {
      "timestamp": "2025-11-26T19:50:02.881652",
      "price": 144.25,
      "change_24h": 6.291052326648093
    },
    {
      "timestamp": "2025-11-26T19:59:46.556976",
      "price": 144.11,
      "change_24h": 5.8127529590233085
    },
    {
      "timestamp": "2025-11-26T20:28:58.306064",
      "price": 143.26,
      "change_24h": 4.623923021836935
    },
    {
      "timestamp": "2025-11-26T20:41:53.693655",
      "price": 142.96,
      "change_24h": 3.975991522519347
    },
    {
      "timestamp": "2025-11-26T20:52:01.937565",
      "price": 142.78,
      "change_24h": 3.715312594943761
    },
    {
      "timestamp": "2025-11-26T21:09:47.150542",
      "price": 143.08,
      "change_24h": 3.9541514844304766
    },
    {
      "timestamp": "2025-11-26T21:28:24.077301",
      "price": 143.39,
      "change_24h": 4.257929543684198
    }
  ]
}