{
  "bitcoin": [
    {
      "timestamp": "2025-12-13T21:28:10.850354",
      "price": 89976,
      "change_24h": -0.2691337391764164
    },
    {
      "timestamp": "2025-12-13T21:40:59.143598",
      "price": 90054,
      "change_24h": -0.25707009068918457
    },
    {
      "timestamp": "2025-12-13T21:50:54.593823",
      "price": 90043,
      "change_24h": -0.26967932291173036
    },
    {
      "timestamp": "2025-12-13T22:00:34.161469",
      "price": 90210,
      "change_24h": -0.02049642865989643
    },
    {
      "timestamp": "2025-12-13T22:27:26.067674",
      "price": 90091,
      "change_24h": -0.2655214629857856
    },
    {
      "timestamp": "2025-12-13T22:42:28.321976",
      "price": 90177,
      "change_24h": -0.18642407272919737
    },
    {
      "timestamp": "2025-12-13T22:52:16.554643",
      "price": 90123,
      "change_24h": -0.17902816406592728
    },
    {
      "timestamp": "2025-12-13T23:11:10.267257",
      "price": 90170,
      "change_24h": -0.2000438262253085
    },
    {
      "timestamp": "2025-12-13T23:29:30.436364",
      "price": 90211,
      "change_24h": -0.16786154611479392
    },
    {
      "timestamp": "2025-12-13T23:42:38.363464",
      "price": 90242,
      "change_24h": -0.14006284565908414
    }
  ],
  "cardano": [
    {
      "timestamp": "2025-12-13T21:28:10.850354",
      "price": 0.409,
      "change_24h": -0.300051820309456
    },
    {
      "timestamp": "2025-12-13T21:40:59.143598",
      "price": 0.407757,
      "change_24h": -0.7193793188858241
    },
    {
      "timestamp": "2025-12-13T21:50:54.593823",
      "price": 0.407935,
      "change_24h": -0.7109640057973925
    },
    {
      "timestamp": "2025-12-13T22:00:34.161469",
      "price": 0.408963,
      "change_24h": -0.3200940446729933
    },
    {
      "timestamp": "2025-12-13T22:27:26.067674",
      "price": 0.40933,
      "change_24h": -0.3473269715597012
    },
    {
      "timestamp": "2025-12-13T22:42:28.321976",
      "price": 0.410114,
      "change_24h": -0.1492324863978093
    },
    {
      "timestamp": "2025-12-13T22:52:16.554643",
      "price": 0.409614,
      "change_24h": -0.3177370944167064
    },
    {
      "timestamp": "2025-12-13T23:11:10.267257",
      "price": 0.408959,
      "change_24h": -0.4319354557124488
    },
    {
      "timestamp": "2025-12-13T23:29:30.436364",
      "price": 0.409964,
      "change_24h": -0.03701494364607086
    },
    {
      "timestamp": "2025-12-13T23:42:38.363464",
      "price": 0.410442,
      "change_24h": 0.3322985542805071
    }
  ],
  "ethereum": [
    {
      "timestamp": "2025-12-13T21:28:10.850354",
      "price": 3102.18,
      "change_24h": 0.5299239901969468
    },
    {
      "timestamp": "2025-12-13T21:40:59.143598",
      "price": 3101.99,
      "change_24h": 0.43487497457832247
    },
    {
      "timestamp": "2025-12-13T21:50:54.593823",
      "price": 3103.02,
      "change_24h": 0.6092186918076672
    },
    {
      "timestamp": "2025-12-13T22:00:34.161469",
      "price": 3112.32,
      "change_24h": 0.9105985071799534
    },
    {
      "timestamp": "2025-12-13T22:27:26.067674",
      "price": 3108.27,
      "change_24h": 0.5754268270638497
    },
    {
      "timestamp": "2025-12-13T22:42:28.321976",
      "price": 3114.07,
      "change_24h": 0.7035294179714673
    },
    {
      "timestamp": "2025-12-13T22:52:16.554643",
      "price": 3112.41,
      "change_24h": 0.749524312873926
    },
    {
      "timestamp": "2025-12-13T23:11:10.267257",
      "price": 3112.43,
      "change_24h": 0.5340503094304865
    },
    {
      "timestamp": "2025-12-13T23:29:30.436364",
      "price": 3113.78,
      "change_24h": 0.7815018810663922
    },
    {
      "timestamp": "2025-12-13T23:42:38.363464",
      "price": 3115.1,
      "change_24h": 0.9174543750420844
    }
  ],
  "litecoin": [
    {
      "timestamp": "2025-12-13T21:28:10.850354",
      "price": 81.18,
      "change_24h": -0.7604676219362336
    },
    {
      "timestamp": "2025-12-13T21:40:59.143598",
      "price": 81.05,
      "change_24h": -1.064131570496327
    },
    {
      "timestamp": "2025-12-13T21:50:54.593823",
      "price": 81.09,
      "change_24h": -1.0448790315674703
    },
    {
      "timestamp": "2025-12-13T22:00:34.161469",
      "price": 81.2,
      "change_24h": -0.8127498100668037
    },
    {
      "timestamp": "2025-12-13T22:27:26.067674",
      "price": 81.3,
      "change_24h": -0.8778870027244687
    },
    {
      "timestamp": "2025-12-13T22:42:28.321976",
      "price": 81.34,
      "change_24h": -0.9314568078908384
    },
    {
      "timestamp": "2025-12-13T22:52:16.554643",
      "price": 81.33,
      "change_24h": -0.8439422132824734
    },
    {
      "timestamp": "2025-12-13T23:11:10.267257",
      "price": 81.28,
      "change_24h": -0.973366709044033
    },
    {
      "timestamp": "2025-12-13T23:29:30.436364",
      "price": 81.36,
      "change_24h": -0.849044126206153
    },
    {
      "timestamp": "2025-12-13T23:42:38.363464",
      "price": 81.45,
      "change_24h": -0.6720602614875569
    }
  ],
  "solana": [
    {
      "timestamp": "2025-12-13T21:28:10.850354",
      "price": 132.28,
      "change_24h": 0.47685261898278897
    },
    {
      "timestamp": "2025-12-13T21:40:59.143598",
      "price": 132.26,
      "change_24h": 0.31876733776595845
    },
    {
      "timestamp": "2025-12-13T21:50:54.593823",
      "price": 132.28,
      "change_24h": 0.24808248912207898
    },
    {
      "timestamp": "2025-12-13T22:00:34.161469",
      "price": 132.49,
      "change_24h": 0.4459096977615725
    },
    {
      "timestamp": "2025-12-13T22:27:26.067674",
      "price": 132.58,
      "change_24h": -0.06621148678460531
    },
    {
      "timestamp": "2025-12-13T22:42:28.321976",
      "price": 132.74,
      "change_24h": 0.14017531246940707
    },
    {
      "timestamp": "2025-12-13T22:52:16.554643",
      "price": 132.88,
      "change_24h": 0.20835417109315219
    },
    {
      "timestamp": "2025-12-13T23:11:10.267257",
      "price": 132.83,
      "change_24h": -0.018410618649742604
    },
    {
      "timestamp": "2025-12-13T23:29:30.436364",
      "price": 132.96,
      "change_24h": 0.16318603525539171
    },
    {
      "timestamp": "2025-12-13T23:42:38.363464",
      "price": 133.08,
      "change_24h": 0.3104528446131352
    }
  ]
}