{
  "bitcoin": [
    {
      "timestamp": "2025-10-12T05:34:26.113879",
      "price": 111568,
      "change_24h": -0.6489706666062526
    },
    {
      "timestamp": "2025-10-12T05:44:09.768463",
      "price": 111594,
      "change_24h": -0.5562884672103263
    },
    {
      "timestamp": "2025-10-12T05:53:48.138282",
      "price": 111783,
      "change_24h": -0.6704870047166889
    },
    {
      "timestamp": "2025-10-12T06:18:59.114179",
      "price": 111855,
      "change_24h": -0.5855305806160293
    },
    {
      "timestamp": "2025-10-12T06:41:23.613569",
      "price": 111779,
      "change_24h": -0.49252165607542636
    },
    {
      "timestamp": "2025-10-12T06:51:15.354987",
      "price": 111928,
      "change_24h": -0.2382450431959773
    },
    {
      "timestamp": "2025-10-12T07:07:36.421653",
      "price": 111775,
      "change_24h": 0.15911097958947695
    },
    {
      "timestamp": "2025-10-12T07:24:23.677673",
      "price": 111921,
      "change_24h": 0.619938544074537
    },
    {
      "timestamp": "2025-10-12T07:35:15.422404",
      "price": 111624,
      "change_24h": 0.7182826435983806
    },
    {
      "timestamp": "2025-10-12T07:45:13.581578",
      "price": 111705,
      "change_24h": 0.954554761890098
    }
  ],
  "cardano": [
    {
      "timestamp": "2025-10-12T05:34:26.113879",
      "price": 0.646621,
      "change_24h": 0.08184712948589981
    },
    {
      "timestamp": "2025-10-12T05:44:09.768463",
      "price": 0.646851,
      "change_24h": 0.360672607687204
    },
    {
      "timestamp": "2025-10-12T05:53:48.138282",
      "price": 0.648353,
      "change_24h": 0.2570626143280428
    },
    {
      "timestamp": "2025-10-12T06:18:59.114179",
      "price": 0.648564,
      "change_24h": -0.7989473922002055
    },
    {
      "timestamp": "2025-10-12T06:41:23.613569",
      "price": 0.648132,
      "change_24h": -1.4878904029754785
    },
    {
      "timestamp": "2025-10-12T06:51:15.354987",
      "price": 0.649988,
      "change_24h": -1.0174052311028452
    },
    {
      "timestamp": "2025-10-12T07:07:36.421653",
      "price": 0.650139,
      "change_24h": 0.05142299137739126
    },
    {
      "timestamp": "2025-10-12T07:24:23.677673",
      "price": 0.649947,
      "change_24h": -0.37439937891553465
    },
    {
      "timestamp": "2025-10-12T07:35:15.422404",
      "price": 0.64773,
      "change_24h": -0.8895954151912759
    },
    {
      "timestamp": "2025-10-12T07:45:13.581578",
      "price": 0.648391,
      "change_24h": -0.289675563360846
    }
  ],
  "ethereum": [
    {
      "timestamp": "2025-10-12T05:34:26.113879",
      "price": 3815.33,
      "change_24h": 1.0669986733085546
    },
    {
      "timestamp": "2025-10-12T05:44:09.768463",
      "price": 3815.21,
      "change_24h": 0.9010293469954562
    },
    {
      "timestamp": "2025-10-12T05:53:48.138282",
      "price": 3815.95,
      "change_24h": 0.35081394972208185
    },
    {
      "timestamp": "2025-10-12T06:18:59.114179",
      "price": 3823.05,
      "change_24h": 0.5191575074405815
    },
    {
      "timestamp": "2025-10-12T06:41:23.613569",
      "price": 3827.65,
      "change_24h": 0.9064116184550091
    },
    {
      "timestamp": "2025-10-12T06:51:15.354987",
      "price": 3835.65,
      "change_24h": 1.3308549983933922
    },
    {
      "timestamp": "2025-10-12T07:07:36.421653",
      "price": 3839.99,
      "change_24h": 1.712497250710567
    },
    {
      "timestamp": "2025-10-12T07:24:23.677673",
      "price": 3837.67,
      "change_24h": 1.7758420556816554
    },
    {
      "timestamp": "2025-10-12T07:35:15.422404",
      "price": 3822.9,
      "change_24h": 1.393705812139479
    },
    {
      "timestamp": "2025-10-12T07:45:13.581578",
      "price": 3826.55,
      "change_24h": 1.7395237787005469
    }
  ],
  "litecoin": [
    {
      "timestamp": "2025-10-12T05:34:26.113879",
      "price": 94.36,
      "change_24h": -4.229924703028103
    },
    {
      "timestamp": "2025-10-12T05:44:09.768463",
      "price": 94.5,
      "change_24h": -3.933710770566302
    },
    {
      "timestamp": "2025-10-12T05:53:48.138282",
      "price": 94.62,
      "change_24h": -4.315398813281361
    },
    {
      "timestamp": "2025-10-12T06:18:59.114179",
      "price": 95.1,
      "change_24h": -4.112683091896823
    },
    {
      "timestamp": "2025-10-12T06:41:23.613569",
      "price": 95.63,
      "change_24h": -4.322982552671799
    },
    {
      "timestamp": "2025-10-12T06:51:15.354987",
      "price": 95.75,
      "change_24h": -3.847391246670039
    },
    {
      "timestamp": "2025-10-12T07:07:36.421653",
      "price": 96.1,
      "change_24h": -2.8741826766606136
    },
    {
      "timestamp": "2025-10-12T07:24:23.677673",
      "price": 96.52,
      "change_24h": -2.7051060586559124
    },
    {
      "timestamp": "2025-10-12T07:35:15.422404",
      "price": 95.74,
      "change_24h": -3.5978720240067945
    },
    {
      "timestamp": "2025-10-12T07:45:13.581578",
      "price": 95.4,
      "change_24h": -3.513590238679462
    }
  ],
  "solana": [
    {
      "timestamp": "2025-10-12T05:34:26.113879",
      "price": 181.33,
      "change_24h": -0.4144614838598971
    },
    {
      "timestamp": "2025-10-12T05:44:09.768463",
      "price": 181.22,
      "change_24h": -0.09190986167214595
    },
    {
      "timestamp": "2025-10-12T05:53:48.138282",
      "price": 181.66,
      "change_24h": -0.329148990326106
    },
    {
      "timestamp": "2025-10-12T06:18:59.114179",
      "price": 181.91,
      "change_24h": -1.2612304444132378
    },
    {
      "timestamp": "2025-10-12T06:41:23.613569",
      "price": 181.84,
      "change_24h": -2.040343849293078
    },
    {
      "timestamp": "2025-10-12T06:51:15.354987",
      "price": 182.42,
      "change_24h": -1.419353905508808
    },
    {
      "timestamp": "2025-10-12T07:07:36.421653",
      "price": 182.61,
      "change_24h": -0.5295321462464844
    },
    {
      "timestamp": "2025-10-12T07:24:23.677673",
      "price": 182.38,
      "change_24h": -0.4180294150336312
    },
    {
      "timestamp": "2025-10-12T07:35:15.422404",
      "price": 182.04,
      "change_24h": -0.370534584644617
    },
    {
      "timestamp": "2025-10-12T07:45:13.581578",
      "price": 182.3,
      "change_24h": -0.1878194544070038
    }
  ]
}