{
  "bitcoin": [
    {
      "timestamp": "2025-10-20T05:54:58.563452",
      "price": 110941,
      "change_24h": 3.8075669827008234
    },
    {
      "timestamp": "2025-10-20T06:26:52.997833",
      "price": 111185,
      "change_24h": 4.080184504853528
    },
    {
      "timestamp": "2025-10-20T06:50:47.048205",
      "price": 111266,
      "change_24h": 4.255332411439352
    },
    {
      "timestamp": "2025-10-20T07:00:57.106928",
      "price": 111303,
      "change_24h": 4.225768511305207
    },
    {
      "timestamp": "2025-10-20T07:27:30.786477",
      "price": 111274,
      "change_24h": 4.1208652937288575
    },
    {
      "timestamp": "2025-10-20T07:40:29.151636",
      "price": 111224,
      "change_24h": 4.109412090354445
    },
    {
      "timestamp": "2025-10-20T07:50:11.338748",
      "price": 111179,
      "change_24h": 4.166056270260423
    },
    {
      "timestamp": "2025-10-20T08:00:04.168349",
      "price": 111198,
      "change_24h": 4.102986006358831
    },
    {
      "timestamp": "2025-10-20T08:35:03.477807",
      "price": 111353,
      "change_24h": 4.347472357338043
    },
    {
      "timestamp": "2025-10-20T08:51:41.446998",
      "price": 111159,
      "change_24h": 4.384455823817625
    }
  ],
  "cardano": [
    {
      "timestamp": "2025-10-20T05:54:58.563452",
      "price": 0.666935,
      "change_24h": 5.5135751915072255
    },
    {
      "timestamp": "2025-10-20T06:26:52.997833",
      "price": 0.672332,
      "change_24h": 6.745388892755116
    },
    {
      "timestamp": "2025-10-20T06:50:47.048205",
      "price": 0.674025,
      "change_24h": 7.277959946947507
    },
    {
      "timestamp": "2025-10-20T07:00:57.106928",
      "price": 0.674545,
      "change_24h": 7.247302892979311
    },
    {
      "timestamp": "2025-10-20T07:27:30.786477",
      "price": 0.671697,
      "change_24h": 6.711150304644842
    },
    {
      "timestamp": "2025-10-20T07:40:29.151636",
      "price": 0.672468,
      "change_24h": 6.890931093087083
    },
    {
      "timestamp": "2025-10-20T07:50:11.338748",
      "price": 0.670138,
      "change_24h": 6.597513356783841
    },
    {
      "timestamp": "2025-10-20T08:00:04.168349",
      "price": 0.668576,
      "change_24h": 6.01045502783485
    },
    {
      "timestamp": "2025-10-20T08:35:03.477807",
      "price": 0.669668,
      "change_24h": 6.412873948391841
    },
    {
      "timestamp": "2025-10-20T08:51:41.446998",
      "price": 0.670257,
      "change_24h": 6.875898520775781
    }
  ],
  "ethereum": [
    {
      "timestamp": "2025-10-20T05:54:58.563452",
      "price": 4067.6,
      "change_24h": 4.363526798321316
    },
    {
      "timestamp": "2025-10-20T06:26:52.997833",
      "price": 4076.73,
      "change_24h": 4.829486735007029
    },
    {
      "timestamp": "2025-10-20T06:50:47.048205",
      "price": 4077.48,
      "change_24h": 5.120716991709
    },
    {
      "timestamp": "2025-10-20T07:00:57.106928",
      "price": 4075.35,
      "change_24h": 5.021072105964809
    },
    {
      "timestamp": "2025-10-20T07:27:30.786477",
      "price": 4070.3,
      "change_24h": 4.729404173955879
    },
    {
      "timestamp": "2025-10-20T07:40:29.151636",
      "price": 4065.42,
      "change_24h": 4.4904913338173476
    },
    {
      "timestamp": "2025-10-20T07:50:11.338748",
      "price": 4057.28,
      "change_24h": 4.546003388095382
    },
    {
      "timestamp": "2025-10-20T08:00:04.168349",
      "price": 4056.17,
      "change_24h": 4.31176699725487
    },
    {
      "timestamp": "2025-10-20T08:35:03.477807",
      "price": 4058.07,
      "change_24h": 4.954057693172046
    },
    {
      "timestamp": "2025-10-20T08:51:41.446998",
      "price": 4043.94,
      "change_24h": 4.707312854155875
    }
  ],
  "litecoin": [
    {
      "timestamp": "2025-10-20T05:54:58.563452",
      "price": 95.18,
      "change_24h": 3.1651637492306066
    },
    {
      "timestamp": "2025-10-20T06:26:52.997833",
      "price": 95.44,
      "change_24h": 3.657360078512004
    },
    {
      "timestamp": "2025-10-20T06:50:47.048205",
      "price": 95.7,
      "change_24h": 3.9876850467738603
    },
    {
      "timestamp": "2025-10-20T07:00:57.106928",
      "price": 95.67,
      "change_24h": 3.89345983734159
    },
    {
      "timestamp": "2025-10-20T07:27:30.786477",
      "price": 95.32,
      "change_24h": 3.661685278097789
    },
    {
      "timestamp": "2025-10-20T07:40:29.151636",
      "price": 95.2,
      "change_24h": 3.606627957875299
    },
    {
      "timestamp": "2025-10-20T07:50:11.338748",
      "price": 95.1,
      "change_24h": 3.5414946875465585
    },
    {
      "timestamp": "2025-10-20T08:00:04.168349",
      "price": 95.0,
      "change_24h": 3.4117579827703
    },
    {
      "timestamp": "2025-10-20T08:35:03.477807",
      "price": 95.16,
      "change_24h": 4.045637439891856
    },
    {
      "timestamp": "2025-10-20T08:51:41.446998",
      "price": 95.01,
      "change_24h": 4.0870239414733796
    }
  ],
  "solana": [
    {
      "timestamp": "2025-10-20T05:54:58.563452",
      "price": 192.78,
      "change_24h": 3.382155212395215
    },
    {
      "timestamp": "2025-10-20T06:26:52.997833",
      "price": 193.31,
      "change_24h": 3.8199515896645373
    },
    {
      "timestamp": "2025-10-20T06:50:47.048205",
      "price": 193.62,
      "change_24h": 4.387917008733464
    },
    {
      "timestamp": "2025-10-20T07:00:57.106928",
      "price": 193.96,
      "change_24h": 4.555659237074404
    },
    {
      "timestamp": "2025-10-20T07:27:30.786477",
      "price": 194.0,
      "change_24h": 4.459534125071421
    },
    {
      "timestamp": "2025-10-20T07:40:29.151636",
      "price": 193.58,
      "change_24h": 4.139034583243239
    },
    {
      "timestamp": "2025-10-20T07:50:11.338748",
      "price": 193.28,
      "change_24h": 4.06742245339217
    },
    {
      "timestamp": "2025-10-20T08:00:04.168349",
      "price": 193.08,
      "change_24h": 3.8948389071365677
    },
    {
      "timestamp": "2025-10-20T08:35:03.477807",
      "price": 193.35,
      "change_24h": 4.606884716066586
    },
    {
      "timestamp": "2025-10-20T08:51:41.446998",
      "price": 193.47,
      "change_24h": 5.073160798686395
    }
  ]
}