{
  "bitcoin": [
    {
      "timestamp": "2026-06-09T21:24:51.382570",
      "price": 61878,
      "change_24h": -2.7958712646002577
    },
    {
      "timestamp": "2026-06-09T22:56:30.962465",
      "price": 61714,
      "change_24h": -2.666915237389155
    },
    {
      "timestamp": "2026-06-10T00:16:12.985326",
      "price": 61776,
      "change_24h": -1.9915302590218384
    },
    {
      "timestamp": "2026-06-10T04:51:42.321517",
      "price": 61296,
      "change_24h": -3.1093684309735643
    },
    {
      "timestamp": "2026-06-10T08:41:30.591411",
      "price": 61286,
      "change_24h": -2.6558451141690993
    },
    {
      "timestamp": "2026-06-10T12:00:01.529461",
      "price": 60996,
      "change_24h": -2.6882388878723114
    },
    {
      "timestamp": "2026-06-10T15:58:58.141006",
      "price": 62666,
      "change_24h": 2.5485555723287665
    },
    {
      "timestamp": "2026-06-10T18:35:14.065196",
      "price": 61882,
      "change_24h": 0.25210000355128004
    },
    {
      "timestamp": "2026-06-10T21:10:59.097172",
      "price": 61577,
      "change_24h": -0.8042248128830701
    },
    {
      "timestamp": "2026-06-10T22:56:42.464093",
      "price": 61379,
      "change_24h": -0.4384787891844969
    }
  ],
  "cardano": [
    {
      "timestamp": "2026-06-09T21:24:51.382570",
      "price": 0.166253,
      "change_24h": -3.5414331384039954
    },
    {
      "timestamp": "2026-06-09T22:56:30.962465",
      "price": 0.165226,
      "change_24h": -3.980856453868636
    },
    {
      "timestamp": "2026-06-10T00:16:12.985326",
      "price": 0.166096,
      "change_24h": -2.2182031904994637
    },
    {
      "timestamp": "2026-06-10T04:51:42.321517",
      "price": 0.161649,
      "change_24h": -3.9095710115271083
    },
    {
      "timestamp": "2026-06-10T08:41:30.591411",
      "price": 0.159138,
      "change_24h": -6.111000949954143
    },
    {
      "timestamp": "2026-06-10T12:00:01.529461",
      "price": 0.159508,
      "change_24h": -4.726068931386201
    },
    {
      "timestamp": "2026-06-10T15:58:58.141006",
      "price": 0.164932,
      "change_24h": 1.0483115448974198
    },
    {
      "timestamp": "2026-06-10T18:35:14.065196",
      "price": 0.161731,
      "change_24h": -2.460396193143451
    },
    {
      "timestamp": "2026-06-10T21:10:59.097172",
      "price": 0.159388,
      "change_24h": -4.6806600768299855
    },
    {
      "timestamp": "2026-06-10T22:56:42.464093",
      "price": 0.160504,
      "change_24h": -2.787702063959764
    }
  ],
  "ethereum": [
    {
      "timestamp": "2026-06-09T21:24:51.382570",
      "price": 1652.63,
      "change_24h": -3.2501603809851183
    },
    {
      "timestamp": "2026-06-09T22:56:30.962465",
      "price": 1641.25,
      "change_24h": -3.5905830847541025
    },
    {
      "timestamp": "2026-06-10T00:16:12.985326",
      "price": 1641.07,
      "change_24h": -3.0343061014265467
    },
    {
      "timestamp": "2026-06-10T04:51:42.321517",
      "price": 1626.12,
      "change_24h": -3.727140007809292
    },
    {
      "timestamp": "2026-06-10T08:41:30.591411",
      "price": 1624.42,
      "change_24h": -3.1731298129496035
    },
    {
      "timestamp": "2026-06-10T12:00:01.529461",
      "price": 1619.11,
      "change_24h": -3.5711996180637557
    },
    {
      "timestamp": "2026-06-10T15:58:58.141006",
      "price": 1658.16,
      "change_24h": 1.374002418880715
    },
    {
      "timestamp": "2026-06-10T18:35:14.065196",
      "price": 1631.05,
      "change_24h": -1.216744617250854
    },
    {
      "timestamp": "2026-06-10T21:10:59.097172",
      "price": 1620.68,
      "change_24h": -2.2754785853498034
    },
    {
      "timestamp": "2026-06-10T22:56:42.464093",
      "price": 1616.99,
      "change_24h": -1.3535478298811228
    }
  ],
  "litecoin": [
    {
      "timestamp": "2026-06-09T21:24:51.382570",
      "price": 43.28,
      "change_24h": -0.7202121152846431
    },
    {
      "timestamp": "2026-06-09T22:56:30.962465",
      "price": 43.01,
      "change_24h": -0.7221389018093693
    },
    {
      "timestamp": "2026-06-10T00:16:12.985326",
      "price": 43.12,
      "change_24h": 0.2249598031354854
    },
    {
      "timestamp": "2026-06-10T04:51:42.321517",
      "price": 42.38,
      "change_24h": -1.2240146118315156
    },
    {
      "timestamp": "2026-06-10T08:41:30.591411",
      "price": 42.32,
      "change_24h": -1.1471190106833618
    },
    {
      "timestamp": "2026-06-10T12:00:01.529461",
      "price": 42.08,
      "change_24h": -0.8427818777667663
    },
    {
      "timestamp": "2026-06-10T15:58:58.141006",
      "price": 42.81,
      "change_24h": 1.915683818947251
    },
    {
      "timestamp": "2026-06-10T18:35:14.065196",
      "price": 41.86,
      "change_24h": -2.6562892100705384
    },
    {
      "timestamp": "2026-06-10T21:10:59.097172",
      "price": 41.52,
      "change_24h": -4.26042194939529
    },
    {
      "timestamp": "2026-06-10T22:56:42.464093",
      "price": 41.56,
      "change_24h": -3.297344627745696
    }
  ],
  "solana": [
    {
      "timestamp": "2026-06-09T21:24:51.382570",
      "price": 65.28,
      "change_24h": -3.7191990005199065
    },
    {
      "timestamp": "2026-06-09T22:56:30.962465",
      "price": 64.93,
      "change_24h": -3.1449818700101893
    },
    {
      "timestamp": "2026-06-10T00:16:12.985326",
      "price": 65.01,
      "change_24h": -2.4078678324747287
    },
    {
      "timestamp": "2026-06-10T04:51:42.321517",
      "price": 64.23,
      "change_24h": -4.274025315438359
    },
    {
      "timestamp": "2026-06-10T08:41:30.591411",
      "price": 63.58,
      "change_24h": -4.57199905670845
    },
    {
      "timestamp": "2026-06-10T12:00:01.529461",
      "price": 63.49,
      "change_24h": -3.8903270674250616
    },
    {
      "timestamp": "2026-06-10T15:58:58.141006",
      "price": 65.35,
      "change_24h": 1.5084206788566341
    },
    {
      "timestamp": "2026-06-10T18:35:14.065196",
      "price": 63.79,
      "change_24h": -1.9223499889752744
    },
    {
      "timestamp": "2026-06-10T21:10:59.097172",
      "price": 62.94,
      "change_24h": -3.8660793272859455
    },
    {
      "timestamp": "2026-06-10T22:56:42.464093",
      "price": 62.79,
      "change_24h": -3.294705538333462
    }
  ]
}