{
  "bitcoin": [
    {
      "timestamp": "2025-12-27T22:50:55.529054",
      "price": 87545,
      "change_24h": 0.17602808761672087
    },
    {
      "timestamp": "2025-12-27T23:00:50.012056",
      "price": 87535,
      "change_24h": 0.08859367265750169
    },
    {
      "timestamp": "2025-12-27T23:27:21.087214",
      "price": 87605,
      "change_24h": 0.21189912391037205
    },
    {
      "timestamp": "2025-12-27T23:41:52.803346",
      "price": 87622,
      "change_24h": 0.31824602104902194
    },
    {
      "timestamp": "2025-12-27T23:51:30.962617",
      "price": 87782,
      "change_24h": 0.5610714581952654
    },
    {
      "timestamp": "2025-12-28T00:57:22.701269",
      "price": 87789,
      "change_24h": 0.5240092504980585
    },
    {
      "timestamp": "2025-12-28T03:06:53.417447",
      "price": 87777,
      "change_24h": 0.42353933947803446
    },
    {
      "timestamp": "2025-12-28T04:14:59.289724",
      "price": 87756,
      "change_24h": 0.3677013997314449
    },
    {
      "timestamp": "2025-12-28T04:56:28.143481",
      "price": 87663,
      "change_24h": 0.28595724643046155
    },
    {
      "timestamp": "2025-12-28T05:25:48.266574",
      "price": 87584,
      "change_24h": 0.2167859494587514
    }
  ],
  "cardano": [
    {
      "timestamp": "2025-12-27T22:50:55.529054",
      "price": 0.363752,
      "change_24h": 4.111632119845631
    },
    {
      "timestamp": "2025-12-27T23:00:50.012056",
      "price": 0.364745,
      "change_24h": 4.254814059851364
    },
    {
      "timestamp": "2025-12-27T23:27:21.087214",
      "price": 0.36621,
      "change_24h": 4.635612641382664
    },
    {
      "timestamp": "2025-12-27T23:41:52.803346",
      "price": 0.366007,
      "change_24h": 4.6328458147119616
    },
    {
      "timestamp": "2025-12-27T23:51:30.962617",
      "price": 0.368017,
      "change_24h": 5.273442542191143
    },
    {
      "timestamp": "2025-12-28T00:57:22.701269",
      "price": 0.36905,
      "change_24h": 5.28623153600927
    },
    {
      "timestamp": "2025-12-28T03:06:53.417447",
      "price": 0.368919,
      "change_24h": 4.5787568764136815
    },
    {
      "timestamp": "2025-12-28T04:14:59.289724",
      "price": 0.369983,
      "change_24h": 4.458599028625063
    },
    {
      "timestamp": "2025-12-28T04:56:28.143481",
      "price": 0.369797,
      "change_24h": 4.814410413181365
    },
    {
      "timestamp": "2025-12-28T05:25:48.266574",
      "price": 0.370184,
      "change_24h": 5.0786111789681225
    }
  ],
  "ethereum": [
    {
      "timestamp": "2025-12-27T22:50:55.529054",
      "price": 2932.6,
      "change_24h": 0.3144809439132789
    },
    {
      "timestamp": "2025-12-27T23:00:50.012056",
      "price": 2932.25,
      "change_24h": 0.11200312789123082
    },
    {
      "timestamp": "2025-12-27T23:27:21.087214",
      "price": 2939.13,
      "change_24h": 0.4043256573717371
    },
    {
      "timestamp": "2025-12-27T23:41:52.803346",
      "price": 2937.81,
      "change_24h": 0.4162218413242514
    },
    {
      "timestamp": "2025-12-27T23:51:30.962617",
      "price": 2948.17,
      "change_24h": 0.7826418520022735
    },
    {
      "timestamp": "2025-12-28T00:57:22.701269",
      "price": 2943.42,
      "change_24h": 0.5999930330818322
    },
    {
      "timestamp": "2025-12-28T03:06:53.417447",
      "price": 2946.07,
      "change_24h": 0.7470667522394459
    },
    {
      "timestamp": "2025-12-28T04:14:59.289724",
      "price": 2944.35,
      "change_24h": 0.5251753713035713
    },
    {
      "timestamp": "2025-12-28T04:56:28.143481",
      "price": 2937.35,
      "change_24h": 0.3269008577370533
    },
    {
      "timestamp": "2025-12-28T05:25:48.266574",
      "price": 2934.07,
      "change_24h": 0.24503988784218156
    }
  ],
  "litecoin": [
    {
      "timestamp": "2025-12-27T22:50:55.529054",
      "price": 79.34,
      "change_24h": 3.576610861447302
    },
    {
      "timestamp": "2025-12-27T23:00:50.012056",
      "price": 79.37,
      "change_24h": 3.4945832532405996
    },
    {
      "timestamp": "2025-12-27T23:27:21.087214",
      "price": 79.88,
      "change_24h": 4.109567297034149
    },
    {
      "timestamp": "2025-12-27T23:41:52.803346",
      "price": 79.85,
      "change_24h": 4.031808439371214
    },
    {
      "timestamp": "2025-12-27T23:51:30.962617",
      "price": 80.0,
      "change_24h": 4.19294135460919
    },
    {
      "timestamp": "2025-12-28T00:57:22.701269",
      "price": 80.19,
      "change_24h": 4.113128777930499
    },
    {
      "timestamp": "2025-12-28T03:06:53.417447",
      "price": 79.56,
      "change_24h": 3.1024054192300783
    },
    {
      "timestamp": "2025-12-28T04:14:59.289724",
      "price": 79.43,
      "change_24h": 2.522378882837683
    },
    {
      "timestamp": "2025-12-28T04:56:28.143481",
      "price": 79.25,
      "change_24h": 2.606087437316993
    },
    {
      "timestamp": "2025-12-28T05:25:48.266574",
      "price": 79.17,
      "change_24h": 2.6021505268206266
    }
  ],
  "solana": [
    {
      "timestamp": "2025-12-27T22:50:55.529054",
      "price": 123.81,
      "change_24h": 1.5015204042142067
    },
    {
      "timestamp": "2025-12-27T23:00:50.012056",
      "price": 123.93,
      "change_24h": 1.4012703836368248
    },
    {
      "timestamp": "2025-12-27T23:27:21.087214",
      "price": 124.2,
      "change_24h": 1.6421149375429778
    },
    {
      "timestamp": "2025-12-27T23:41:52.803346",
      "price": 124.25,
      "change_24h": 1.6022915650647163
    },
    {
      "timestamp": "2025-12-27T23:51:30.962617",
      "price": 124.5,
      "change_24h": 1.8907949385325233
    },
    {
      "timestamp": "2025-12-28T00:57:22.701269",
      "price": 124.4,
      "change_24h": 1.9697197192158906
    },
    {
      "timestamp": "2025-12-28T03:06:53.417447",
      "price": 124.14,
      "change_24h": 1.5233709683199674
    },
    {
      "timestamp": "2025-12-28T04:14:59.289724",
      "price": 124.11,
      "change_24h": 0.6063323792930956
    },
    {
      "timestamp": "2025-12-28T04:56:28.143481",
      "price": 124.03,
      "change_24h": 0.8768260996361759
    },
    {
      "timestamp": "2025-12-28T05:25:48.266574",
      "price": 123.72,
      "change_24h": 0.6304809120495339
    }
  ]
}